{
  "required": true,
  "minVersion": "0.8",
  "package": "com.hecookin.adastramekanized.mixins",
  "compatibilityLevel": "JAVA_17",
  "refmap": "adastramekanized.refmap.json",
  "mixins": [
    "LivingEntityAccessor"
  ],
  "client": [
    "LevelRendererMixin",
    "CustomDyeableArmorItemMixin",
    "HumanoidModelMixin",
    "client.LoadingOverlayMixin",
    "client.LoadingOverlayAccessor",
    "client.TitleScreenMixin",
    "client.PauseScreenMixin",
    "client.SelectWorldScreenMixin",
    "client.CreateWorldScreenMixin",
    "client.RotatingCubeMapRendererMixin"
  ],
  "server": [],
  "injectors": {
    "defaultRequire": 1
  }
}