{
  "type": "adastramekanized:nasa_workbench",
  "ingredients": [
    {
      "item": "adastramekanized:gas_tank"
    },
    {
      "item": "create:iron_sheet"
    },
    {
      "item": "adastramekanized:steel_rod"
    },
    {
      "item": "adastramekanized:steel_sheet"
    },
    {
      "item": "adastramekanized:steel_rod"
    },
    {
      "item": "adastramekanized:steel_rod"
    },
    {
      "item": "adastramekanized:steel_rod"
    },
    {
      "item": "adastramekanized:steel_sheet"
    },
    {
      "item": "adastramekanized:steel_sheet"
    },
    {
      "item": "adastramekanized:steel_sheet"
    },
    {
      "item": "adastramekanized:steel_sheet"
    }
  ],
  "result": {
    "count": 1,
    "id": "adastramekanized:steel_tank"
  }
}