{
  "type": "adastramekanized:pluto",
  "generator": {
    "type": "minecraft:noise",
    "settings": "adastramekanized:pluto",
    "biome_source": {
      "type": "minecraft:multi_noise",
      "biomes": [
        {
          "biome": "adastramekanized:pluto_snowy_plains",
          "parameters": {
            "temperature": -1.0,
            "humidity": -0.9,
            "continentalness": 0.0,
            "erosion": 0.0,
            "depth": 0.0,
            "weirdness": 0.0,
            "offset": 0.0
          }
        }
      ]
    }
  }
}